[{
        "imageURL": "Assets/Images/CTMCpp.png",
        "name": "Book1",
        "category": ["cpp"],
        "description": "",
        "link": "https://mbktechstudio.com/Assets/MBK_CV.pdf"
    },
    {
        "imageURL": "Assets/Images/unity.png",
        "name": "Book2",
        "category": ["unity"],
        "description": "",
        "link": "https://mbktechstudio.com/Assets/MBK_CV.pdf"
    },
    {
        "imageURL": "Assets/Images/cpp.png",
        "name": "Book3",
        "category": ["cpp"],
        "description": "",
        "link": "https://mbktechstudio.com/Assets/MBK_CV.pdf"
    },
    {
        "imageURL": "Assets/Images/mainpage.png",
        "name": "Book4",
        "category": ["web"],
        "description": "",
        "link": "https://mbktechstudio.com/Assets/MBK_CV.pdf"
    },
    {
        "imageURL": "Assets/Images/unity.png",
        "name": "Book5",
        "category": ["unity"],
        "description": "",
        "link": "https://mbktechstudio.com/Assets/MBK_CV.pdf"
    }
]
